setup.py
scripts/yasd
yasd/__init__.py
yasd/procstat.py
yasd/recvmmsg.py
yasd/stats.py
yasd.egg-info/PKG-INFO
yasd.egg-info/SOURCES.txt
yasd.egg-info/dependency_links.txt
yasd.egg-info/requires.txt
yasd.egg-info/top_level.txt