Metadata-Version: 1.1
Name: yasd
Version: 1.0.2
Summary: Yet Another Syslog Daemon
Home-page: https://github.com/nikicat/yasd
Author: Nikolay Bryskin
Author-email: devel.niks@gmail.com
License: UNKNOWN
Platform: UNKNOWN
Classifier: Development Status :: 4 - Beta
Classifier: Environment :: Console
Classifier: Intended Audience :: Developers
Classifier: Intended Audience :: System Administrators
Classifier: License :: OSI Approved :: GNU General Public License v3 (GPLv3)
Classifier: Operating System :: POSIX :: Linux
Classifier: Programming Language :: Python :: 3
Classifier: Topic :: System :: Networking :: Monitoring
